mmu.libs/libgomp-a34b3233.so.1.0.0
mmu/__init__.py
mmu/version.py
mmu/metrics/__init__.py
mmu/metrics/utils.py
mmu/metrics/pr_lep.py
mmu/metrics/metrics.py
mmu/metrics/confmat.py
mmu/viz/__init__.py
mmu/viz/contours.py
mmu/viz/ellipse.py
mmu/viz/utils.py
mmu/methods/__init__.py
mmu/methods/pointbase.py
mmu/methods/prcurve.py
mmu/methods/curvebase.py
mmu/methods/prpoint.py
mmu/methods/rocpoint.py
mmu/methods/roccurve.py
mmu/lib/__init__.py
mmu/lib/_mmu_core.cpython-39-x86_64-linux-gnu.so
mmu/commons/types.py
mmu/commons/__init__.py
mmu/commons/utils.py
mmu/commons/checks.py
mmu/commons/_testing/__init__.py
mmu/commons/_testing/utils.py
mmu-0.2.2.dist-info/RECORD
mmu-0.2.2.dist-info/METADATA
mmu-0.2.2.dist-info/NOTICE
mmu-0.2.2.dist-info/top_level.txt
mmu-0.2.2.dist-info/LICENSE
mmu-0.2.2.dist-info/WHEEL
