Metadata-Version: 2.1
Name: mmu
Version: 0.2.2
Summary: Compute uncertainties on classification model metrics.
Home-page: https://github.com/RUrlus/ModelMetricUncertainty
Author: Ralph Urlus
Author-email: rurlus.dev@gmail.com
License: Apache-2
Project-URL: Source, https://github.com/RUrlus/ModelMetricUncertainty
Project-URL: Tracker, https://github.com/RUrlus/ModelMetricUncertainty/issues
Keywords: uncertainty classification metrics
Platform: any
Requires-Python: >=3.7
License-File: LICENSE
License-File: NOTICE
Requires-Dist: numpy (>=1.18)
Requires-Dist: scipy (>=1.5.2)
Requires-Dist: pandas (>=0.25.1)
Requires-Dist: matplotlib (>=2.2.3)
Requires-Dist: scikit-learn (>=1.0)
Provides-Extra: all
Requires-Dist: pytest ; extra == 'all'
Provides-Extra: test
Requires-Dist: pytest ; extra == 'test'
